jsondb/__init__.py
jsondb/jsondtb.py
jsondtb-0.0.1.dist-info/LICENCE
jsondtb-0.0.1.dist-info/METADATA
jsondtb-0.0.1.dist-info/WHEEL
jsondtb-0.0.1.dist-info/top_level.txt
jsondtb-0.0.1.dist-info/RECORD
