Metadata-Version: 2.1
Name: jsondtb
Version: 0.0.1
Summary: Use A Json File As Your Database
Home-page: UNKNOWN
Author: Winning godspower 
Author-email: <winninggodspower@gmail.com>
License: UNKNOWN
Requires-Dist: cryptography
